realtime_trains/__init__.py
realtime_trains/api.py
realtime_trains/models.py
realtime_trains-0.0.5.dist-info/LICENSE
realtime_trains-0.0.5.dist-info/METADATA
realtime_trains-0.0.5.dist-info/WHEEL
realtime_trains-0.0.5.dist-info/RECORD
