Metadata-Version: 2.1
Name: realtime-trains
Version: 0.0.5
Summary: An unofficial Python library for Realtime Trains API
Author: Marko B
Requires-Python: >=3.10,<4.0
Classifier: License :: OSI Approved :: MIT License
Classifier: Operating System :: OS Independent
Classifier: Programming Language :: Python :: 3
Classifier: Programming Language :: Python :: 3.10
Classifier: Programming Language :: Python :: 3.11
Classifier: Programming Language :: Python :: 3.12
Requires-Dist: httpx (>=0.25.1,<0.26.0)
Requires-Dist: pydantic (>=2.5.2,<3.0.0)
Requires-Dist: python-dateutil (>=2.8.2,<3.0.0)
